pip_services4_mqtt/__init__.py
pip_services4_mqtt/build/DefaultMqttFactory.py
pip_services4_mqtt/build/MqttMessageQueueFactory.py
pip_services4_mqtt/build/__init__.py
pip_services4_mqtt/connect/IMqttMessageListener.py
pip_services4_mqtt/connect/MqttConnection.py
pip_services4_mqtt/connect/MqttConnectionResolver.py
pip_services4_mqtt/connect/MqttSubscription.py
pip_services4_mqtt/connect/__init__.py
pip_services4_mqtt/queues/MqttMessageQueue.py
pip_services4_mqtt/queues/__init__.py
pip_services4_mqtt-0.0.1.dist-info/LICENSE
pip_services4_mqtt-0.0.1.dist-info/METADATA
pip_services4_mqtt-0.0.1.dist-info/WHEEL
pip_services4_mqtt-0.0.1.dist-info/top_level.txt
pip_services4_mqtt-0.0.1.dist-info/zip-safe
pip_services4_mqtt-0.0.1.dist-info/RECORD
